Metadata-Version: 1.1
Name: django-endesive
Version: 0.1.0
Summary: Django endesive PDF digital signing utility.
Home-page: https://github.com/zengoma/django-endesive
Author: Lance Moore
Author-email: lance@adminout.net
License: MIT
Keywords: django-endesive
Platform: UNKNOWN
Classifier: Development Status :: 3 - Alpha
Classifier: Framework :: Django :: 1.11
Classifier: Framework :: Django :: 2.0
Classifier: Intended Audience :: Developers
Classifier: License :: OSI Approved :: MIT License
Classifier: Natural Language :: English
Classifier: Programming Language :: Python :: 2
Classifier: Programming Language :: Python :: 2.7
Classifier: Programming Language :: Python :: 3
Classifier: Programming Language :: Python :: 3.4
Classifier: Programming Language :: Python :: 3.6
